setup.py
umap/__init__.py
umap/get.py
umap.egg-info/PKG-INFO
umap.egg-info/SOURCES.txt
umap.egg-info/dependency_links.txt
umap.egg-info/top_level.txt