Metadata-Version: 1.0
Name: umap
Version: 0.1
Summary: UNIST synthesis MAP solution
Home-page: http://amath.unist.ac.kr
Author: Kyunghoon Kim
Author-email: preware@gmail.com
License: UNKNOWN
Platform: UNKNOWN
